ceurspt/__init__.py
ceurspt/bibtex.py
ceurspt/ceurws.py
ceurspt/ceurws_base.py
ceurspt/dataclass_util.py
ceurspt/profiler.py
ceurspt/spt_cmd.py
ceurspt/version.py
ceurspt/webserver.py
ceurspt/models/__init__.py
ceurspt/models/dblp.py
pyceurspt-0.0.6.dist-info/METADATA
pyceurspt-0.0.6.dist-info/WHEEL
pyceurspt-0.0.6.dist-info/entry_points.txt
pyceurspt-0.0.6.dist-info/licenses/LICENSE
pyceurspt-0.0.6.dist-info/RECORD
