Metadata-Version: 2.1
Name: pyCEURspt
Version: 0.0.6
Project-URL: Home, https://github.com/ceurws/ceur-spt
Project-URL: Documentation, https://github.com/ceurws/ceur-spt
Project-URL: Source, https://github.com/ceurws/ceur-spt
Author-email: Tim Holzheim <tim.holzheim@rwth-aachen.de>, Wolfgang Fahl <wf@bitplan.com>
Maintainer-email: Wolfgang Fahl <wf@bitplan.com>, Tim Holzheim <tim.holzheim@rwth-aachen.de>
License-Expression: Apache-2.0
License-File: LICENSE
Classifier: Development Status :: 4 - Beta
Classifier: Environment :: Web Environment
Classifier: Intended Audience :: Developers
Classifier: Intended Audience :: Education
Classifier: Intended Audience :: Science/Research
Classifier: License :: OSI Approved :: Apache Software License
Classifier: Operating System :: OS Independent
Classifier: Programming Language :: Python :: 3 :: Only
Classifier: Programming Language :: Python :: 3.8
Classifier: Programming Language :: Python :: 3.9
Classifier: Programming Language :: Python :: 3.10
Classifier: Programming Language :: Python :: 3.11
Classifier: Topic :: Software Development :: Libraries :: Python Modules
Requires-Python: >=3.8
Requires-Dist: beautifulsoup4
Requires-Dist: bibtexparser
Requires-Dist: fastapi[all]
Requires-Dist: linkml-runtime
Requires-Dist: orjson>=3.8.9
Requires-Dist: tqdm
Requires-Dist: uvicorn
Provides-Extra: test
Requires-Dist: green; extra == 'test'
